spatialmst/__init__.py
spatialmst/common.py
spatialmst/spatialmst.py
spatialmst/layers/IntegrationLayer.py
spatialmst/layers/__init__.py
spatialmst/model/MSTDecoder.py
spatialmst/model/MSTEncoder.py
spatialmst/model/__init__.py
spatialmst/modules/__init__.py
spatialmst/modules/metabolic_modality.py
spatialmst/modules/transcriptomic_modality.py
spatialmst/train/SpatialMST_Trainer.py
spatialmst/train/__init__.py
spatialmst/utils/__init__.py
spatialmst/utils/dataloader.py
spatialmst/utils/util.py
spatialmst-0.0.3.dist-info/licenses/AUTHORS.rst
spatialmst-0.0.3.dist-info/licenses/LICENSE
spatialmst-0.0.3.dist-info/METADATA
spatialmst-0.0.3.dist-info/WHEEL
spatialmst-0.0.3.dist-info/entry_points.txt
spatialmst-0.0.3.dist-info/top_level.txt
spatialmst-0.0.3.dist-info/RECORD
