Metadata-Version: 2.4
Name: SpatialMST
Version: 0.0.3
Summary: Spatial Multimodal Self-supervised Transformer
Author-email: Suraj Verma <verma.surajcool@gmail.com>
License: MIT License
Project-URL: Homepage, https://github.com/Angione-Lab/SpatialMST
Keywords: SpatialMST
Classifier: Intended Audience :: Developers
Classifier: License :: OSI Approved :: MIT License
Classifier: Natural Language :: English
Classifier: Programming Language :: Python :: 3.9
Classifier: Programming Language :: Python :: 3.10
Classifier: Programming Language :: Python :: 3.11
Classifier: Programming Language :: Python :: 3.12
Requires-Python: >=3.9
License-File: LICENSE
License-File: AUTHORS.rst
Requires-Dist: NumPy==1.26.4
Requires-Dist: scanpy
Requires-Dist: mudata
Requires-Dist: pandas==2.2.3
Requires-Dist: torch_geometric
Requires-Dist: torch
Requires-Dist: matplotlib
Requires-Dist: scikit-learn
Requires-Dist: scipy
Requires-Dist: beautifulsoup4
Requires-Dist: lightning
Requires-Dist: magic-impute
Provides-Extra: all
Requires-Dist: SpatialMST[extra]; extra == "all"
Provides-Extra: extra
Requires-Dist: pandas; extra == "extra"
Dynamic: license-file
